{"ticker":"ABVC","name":"ABVC BIOPHARMA, INC.","sector":null,"exchange":null,"quarters":[{"date":"2010-09-30","revenue":null,"eps":null,"netIncome":null,"grossProfit":null,"operatingIncome":null,"freeCashFlow":null,"sharesOutstanding":null,"totalAssets":null,"totalLiabilities":null,"totalDebt":null,"cashAndEquivalents":2814.0,"stockholdersEquity":-2993817.0},{"date":"2010-12-31","revenue":2470.0,"eps":null,"netIncome":-423939.0,"grossProfit":null,"operatingIncome":-368177.0,"freeCashFlow":null,"sharesOutstanding":null,"totalAssets":null,"totalLiabilities":null,"totalDebt":null,"cashAndEquivalents":20221.0,"stockholdersEquity":null},{"date":"2011-03-31","revenue":720.0,"eps":null,"netIncome":482734.0,"grossProfit":null,"operatingIncome":-328716.0,"freeCashFlow":null,"sharesOutstanding":null,"totalAssets":null,"totalLiabilities":null,"totalDebt":null,"cashAndEquivalents":null,"stockholdersEquity":null},{"date":"2011-09-30","revenue":null,"eps":null,"netIncome":null,"grossProfit":null,"operatingIncome":null,"freeCashFlow":null,"sharesOutstanding":null,"totalAssets":369396.0,"totalLiabilities":null,"totalDebt":null,"cashAndEquivalents":71784.0,"stockholdersEquity":-1463673.0},{"date":"2011-12-31","revenue":2049.0,"eps":null,"netIncome":-277139.0,"grossProfit":null,"operatingIncome":-458977.0,"freeCashFlow":-366980.0,"sharesOutstanding":16331882.0,"totalAssets":329087.0,"totalLiabilities":null,"totalDebt":null,"cashAndEquivalents":30197.0,"stockholdersEquity":-1348821.0},{"date":"2012-01-31","revenue":null,"eps":null,"netIncome":null,"grossProfit":null,"operatingIncome":null,"freeCashFlow":null,"sharesOutstanding":16331882.0,"totalAssets":null,"totalLiabilities":null,"totalDebt":null,"cashAndEquivalents":null,"stockholdersEquity":null},{"date":"2012-03-31","revenue":3665.0,"eps":null,"netIncome":-342840.0,"grossProfit":null,"operatingIncome":-330553.0,"freeCashFlow":null,"sharesOutstanding":null,"totalAssets":290563.0,"totalLiabilities":null,"totalDebt":null,"cashAndEquivalents":0.0,"stockholdersEquity":-1384162.0},{"date":"2012-06-30","revenue":0.0,"eps":null,"netIncome":-258946.0,"grossProfit":null,"operatingIncome":-245447.0,"freeCashFlow":null,"sharesOutstanding":null,"totalAssets":null,"totalLiabilities":null,"totalDebt":null,"cashAndEquivalents":62875.0,"stockholdersEquity":null},{"date":"2012-09-30","revenue":null,"eps":null,"netIncome":null,"grossProfit":null,"operatingIncome":null,"freeCashFlow":null,"sharesOutstanding":null,"totalAssets":302308.0,"totalLiabilities":null,"totalDebt":null,"cashAndEquivalents":13386.0,"stockholdersEquity":-1643778.0},{"date":"2012-12-31","revenue":7026.0,"eps":null,"netIncome":-153803.0,"grossProfit":null,"operatingIncome":-137434.0,"freeCashFlow":-36350.0,"sharesOutstanding":54593032.0,"totalAssets":271793.0,"totalLiabilities":null,"totalDebt":null,"cashAndEquivalents":2036.0,"stockholdersEquity":-1800929.0},{"date":"2013-03-31","revenue":761.0,"eps":null,"netIncome":-104276.0,"grossProfit":null,"operatingIncome":-20452.0,"freeCashFlow":null,"sharesOutstanding":null,"totalAssets":251342.0,"totalLiabilities":null,"totalDebt":null,"cashAndEquivalents":788.0,"stockholdersEquity":-1840916.0},{"date":"2013-06-30","revenue":0.0,"eps":null,"netIncome":-103547.0,"grossProfit":null,"operatingIncome":-19373.0,"freeCashFlow":null,"sharesOutstanding":null,"totalAssets":231969.0,"totalLiabilities":null,"totalDebt":null,"cashAndEquivalents":618.0,"stockholdersEquity":-1880174.0},{"date":"2013-09-30","revenue":null,"eps":null,"netIncome":null,"grossProfit":null,"operatingIncome":null,"freeCashFlow":null,"sharesOutstanding":null,"totalAssets":231969.0,"totalLiabilities":null,"totalDebt":null,"cashAndEquivalents":618.0,"stockholdersEquity":-1880174.0},{"date":"2013-12-31","revenue":0.0,"eps":null,"netIncome":-10.0,"grossProfit":null,"operatingIncome":-10.0,"freeCashFlow":null,"sharesOutstanding":null,"totalAssets":231959.0,"totalLiabilities":null,"totalDebt":null,"cashAndEquivalents":608.0,"stockholdersEquity":-1880184.0},{"date":"2014-03-31","revenue":0.0,"eps":null,"netIncome":-30.0,"grossProfit":0.0,"operatingIncome":-30.0,"freeCashFlow":null,"sharesOutstanding":null,"totalAssets":231929.0,"totalLiabilities":null,"totalDebt":null,"cashAndEquivalents":578.0,"stockholdersEquity":-1880214.0},{"date":"2014-06-30","revenue":0.0,"eps":null,"netIncome":-30.0,"grossProfit":0.0,"operatingIncome":-30.0,"freeCashFlow":null,"sharesOutstanding":null,"totalAssets":231899.0,"totalLiabilities":null,"totalDebt":null,"cashAndEquivalents":548.0,"stockholdersEquity":-1880244.0},{"date":"2014-09-18","revenue":null,"eps":null,"netIncome":null,"grossProfit":null,"operatingIncome":null,"freeCashFlow":null,"sharesOutstanding":null,"totalAssets":null,"totalLiabilities":null,"totalDebt":null,"cashAndEquivalents":null,"stockholdersEquity":54594.0},{"date":"2014-09-30","revenue":0.0,"eps":null,"netIncome":-23235.0,"grossProfit":0.0,"operatingIncome":null,"freeCashFlow":null,"sharesOutstanding":null,"totalAssets":65389.0,"totalLiabilities":34030.0,"totalDebt":null,"cashAndEquivalents":0.0,"stockholdersEquity":31359.0},{"date":"2014-12-31","revenue":0.0,"eps":null,"netIncome":-1030.0,"grossProfit":null,"operatingIncome":-1030.0,"freeCashFlow":null,"sharesOutstanding":54593032.0,"totalAssets":64594.0,"totalLiabilities":null,"totalDebt":null,"cashAndEquivalents":0.0,"stockholdersEquity":29534.0},{"date":"2015-03-31","revenue":2260.0,"eps":null,"netIncome":1119.0,"grossProfit":1959.0,"operatingIncome":1119.0,"freeCashFlow":null,"sharesOutstanding":54593032.0,"totalAssets":67348.0,"totalLiabilities":null,"totalDebt":null,"cashAndEquivalents":0.0,"stockholdersEquity":31448.0},{"date":"2015-06-30","revenue":0.0,"eps":null,"netIncome":-1500.0,"grossProfit":0.0,"operatingIncome":-1500.0,"freeCashFlow":null,"sharesOutstanding":54593032.0,"totalAssets":67348.0,"totalLiabilities":null,"totalDebt":null,"cashAndEquivalents":2260.0,"stockholdersEquity":29948.0},{"date":"2015-07-20","revenue":null,"eps":null,"netIncome":null,"grossProfit":null,"operatingIncome":null,"freeCashFlow":null,"sharesOutstanding":null,"totalAssets":null,"totalLiabilities":null,"totalDebt":null,"cashAndEquivalents":null,"stockholdersEquity":897001.0},{"date":"2015-07-31","revenue":null,"eps":null,"netIncome":null,"grossProfit":null,"operatingIncome":null,"freeCashFlow":null,"sharesOutstanding":54593032.0,"totalAssets":null,"totalLiabilities":null,"totalDebt":null,"cashAndEquivalents":null,"stockholdersEquity":null},{"date":"2015-09-30","revenue":null,"eps":0.0,"netIncome":-315602.0,"grossProfit":null,"operatingIncome":-315602.0,"freeCashFlow":null,"sharesOutstanding":null,"totalAssets":1002460.0,"totalLiabilities":369103.0,"totalDebt":null,"cashAndEquivalents":994830.0,"stockholdersEquity":633357.0},{"date":"2015-11-25","revenue":null,"eps":null,"netIncome":null,"grossProfit":null,"operatingIncome":null,"freeCashFlow":null,"sharesOutstanding":60011144.0,"totalAssets":null,"totalLiabilities":null,"totalDebt":null,"cashAndEquivalents":null,"stockholdersEquity":null},{"date":"2015-12-31","revenue":null,"eps":-0.02,"netIncome":-3501413.0,"grossProfit":null,"operatingIncome":-3501605.0,"freeCashFlow":null,"sharesOutstanding":60011144.0,"totalAssets":64905.0,"totalLiabilities":null,"totalDebt":null,"cashAndEquivalents":423965.0,"stockholdersEquity":64905.0},{"date":"2016-02-18","revenue":null,"eps":null,"netIncome":null,"grossProfit":null,"operatingIncome":null,"freeCashFlow":null,"sharesOutstanding":66422502.0,"totalAssets":null,"totalLiabilities":null,"totalDebt":null,"cashAndEquivalents":null,"stockholdersEquity":null},{"date":"2016-03-30","revenue":null,"eps":null,"netIncome":null,"grossProfit":null,"operatingIncome":null,"freeCashFlow":null,"sharesOutstanding":null,"totalAssets":876454.0,"totalLiabilities":10005723.0,"totalDebt":null,"cashAndEquivalents":872639.0,"stockholdersEquity":-9129269.0},{"date":"2016-03-31","revenue":null,"eps":null,"netIncome":-6608712.0,"grossProfit":-32.0,"operatingIncome":-6608764.0,"freeCashFlow":null,"sharesOutstanding":66422502.0,"totalAssets":876454.0,"totalLiabilities":5723.0,"totalDebt":null,"cashAndEquivalents":872639.0,"stockholdersEquity":870731.0},{"date":"2016-05-16","revenue":null,"eps":null,"netIncome":null,"grossProfit":null,"operatingIncome":null,"freeCashFlow":null,"sharesOutstanding":208758987.0,"totalAssets":null,"totalLiabilities":null,"totalDebt":null,"cashAndEquivalents":null,"stockholdersEquity":null},{"date":"2016-06-30","revenue":null,"eps":null,"netIncome":-293237.0,"grossProfit":null,"operatingIncome":-289098.0,"freeCashFlow":null,"sharesOutstanding":209352897.0,"totalAssets":88719.0,"totalLiabilities":8561446.0,"totalDebt":null,"cashAndEquivalents":84904.0,"stockholdersEquity":-8472727.0},{"date":"2016-08-10","revenue":null,"eps":null,"netIncome":null,"grossProfit":null,"operatingIncome":null,"freeCashFlow":null,"sharesOutstanding":209352897.0,"totalAssets":null,"totalLiabilities":null,"totalDebt":null,"cashAndEquivalents":null,"stockholdersEquity":null},{"date":"2016-09-30","revenue":null,"eps":null,"netIncome":null,"grossProfit":null,"operatingIncome":null,"freeCashFlow":null,"sharesOutstanding":null,"totalAssets":177352.0,"totalLiabilities":6556470.0,"totalDebt":null,"cashAndEquivalents":173537.0,"stockholdersEquity":-6379118.0},{"date":"2016-10-01","revenue":null,"eps":null,"netIncome":null,"grossProfit":null,"operatingIncome":null,"freeCashFlow":null,"sharesOutstanding":null,"totalAssets":null,"totalLiabilities":null,"totalDebt":null,"cashAndEquivalents":173537.0,"stockholdersEquity":null},{"date":"2016-12-31","revenue":70000.0,"eps":0.0,"netIncome":-140337.0,"grossProfit":70000.0,"operatingIncome":-140386.0,"freeCashFlow":null,"sharesOutstanding":null,"totalAssets":18645.0,"totalLiabilities":6538100.0,"totalDebt":null,"cashAndEquivalents":18645.0,"stockholdersEquity":-6519455.0},{"date":"2017-01-06","revenue":null,"eps":null,"netIncome":null,"grossProfit":null,"operatingIncome":null,"freeCashFlow":null,"sharesOutstanding":210821647.0,"totalAssets":null,"totalLiabilities":null,"totalDebt":null,"cashAndEquivalents":null,"stockholdersEquity":null},{"date":"2017-01-11","revenue":null,"eps":null,"netIncome":null,"grossProfit":null,"operatingIncome":null,"freeCashFlow":null,"sharesOutstanding":213746647.0,"totalAssets":null,"totalLiabilities":null,"totalDebt":null,"cashAndEquivalents":null,"stockholdersEquity":null},{"date":"2017-02-14","revenue":null,"eps":null,"netIncome":null,"grossProfit":null,"operatingIncome":null,"freeCashFlow":null,"sharesOutstanding":210821647.0,"totalAssets":null,"totalLiabilities":null,"totalDebt":null,"cashAndEquivalents":null,"stockholdersEquity":null},{"date":"2017-03-31","revenue":null,"eps":0.0,"netIncome":-256671.0,"grossProfit":null,"operatingIncome":-236841.0,"freeCashFlow":null,"sharesOutstanding":null,"totalAssets":106410.0,"totalLiabilities":1029160.0,"totalDebt":null,"cashAndEquivalents":106410.0,"stockholdersEquity":-922750.0},{"date":"2017-05-19","revenue":null,"eps":null,"netIncome":null,"grossProfit":null,"operatingIncome":null,"freeCashFlow":null,"sharesOutstanding":213746647.0,"totalAssets":null,"totalLiabilities":null,"totalDebt":null,"cashAndEquivalents":null,"stockholdersEquity":null},{"date":"2017-06-30","revenue":90000.0,"eps":0.0,"netIncome":-217879.0,"grossProfit":90000.0,"operatingIncome":-189479.0,"freeCashFlow":null,"sharesOutstanding":null,"totalAssets":8053.0,"totalLiabilities":1056130.0,"totalDebt":null,"cashAndEquivalents":8053.0,"stockholdersEquity":-1048077.0},{"date":"2017-08-18","revenue":null,"eps":null,"netIncome":null,"grossProfit":null,"operatingIncome":null,"freeCashFlow":null,"sharesOutstanding":213746647.0,"totalAssets":null,"totalLiabilities":null,"totalDebt":null,"cashAndEquivalents":null,"stockholdersEquity":null},{"date":"2017-09-30","revenue":null,"eps":-0.02,"netIncome":-3387096.0,"grossProfit":null,"operatingIncome":-3359636.0,"freeCashFlow":null,"sharesOutstanding":213746647.0,"totalAssets":2754851.0,"totalLiabilities":4147914.0,"totalDebt":null,"cashAndEquivalents":204851.0,"stockholdersEquity":-1393063.0},{"date":"2017-12-31","revenue":null,"eps":null,"netIncome":null,"grossProfit":null,"operatingIncome":null,"freeCashFlow":null,"sharesOutstanding":null,"totalAssets":2643332.0,"totalLiabilities":4400247.0,"totalDebt":null,"cashAndEquivalents":350257.0,"stockholdersEquity":-1756915.0},{"date":"2018-03-31","revenue":null,"eps":-0.05,"netIncome":-713622.0,"grossProfit":null,"operatingIncome":-674199.0,"freeCashFlow":null,"sharesOutstanding":null,"totalAssets":2555675.0,"totalLiabilities":4489004.0,"totalDebt":null,"cashAndEquivalents":174444.0,"stockholdersEquity":-1933329.0},{"date":"2018-05-15","revenue":null,"eps":null,"netIncome":null,"grossProfit":null,"operatingIncome":null,"freeCashFlow":null,"sharesOutstanding":213926475.0,"totalAssets":null,"totalLiabilities":null,"totalDebt":null,"cashAndEquivalents":null,"stockholdersEquity":null},{"date":"2018-06-30","revenue":3229.0,"eps":-0.05,"netIncome":-736040.0,"grossProfit":910.0,"operatingIncome":-524432.0,"freeCashFlow":null,"sharesOutstanding":null,"totalAssets":2649532.0,"totalLiabilities":4887243.0,"totalDebt":null,"cashAndEquivalents":309251.0,"stockholdersEquity":-2237711.0},{"date":"2018-08-17","revenue":null,"eps":null,"netIncome":null,"grossProfit":null,"operatingIncome":null,"freeCashFlow":null,"sharesOutstanding":213926475.0,"totalAssets":null,"totalLiabilities":null,"totalDebt":null,"cashAndEquivalents":null,"stockholdersEquity":null},{"date":"2018-09-30","revenue":747.0,"eps":0.0,"netIncome":-687300.0,"grossProfit":210.0,"operatingIncome":-396285.0,"freeCashFlow":null,"sharesOutstanding":213926475.0,"totalAssets":2594389.0,"totalLiabilities":5043098.0,"totalDebt":null,"cashAndEquivalents":4389.0,"stockholdersEquity":-2448709.0},{"date":"2018-11-13","revenue":null,"eps":null,"netIncome":null,"grossProfit":null,"operatingIncome":null,"freeCashFlow":null,"sharesOutstanding":213926475.0,"totalAssets":null,"totalLiabilities":null,"totalDebt":null,"cashAndEquivalents":null,"stockholdersEquity":null},{"date":"2018-12-31","revenue":null,"eps":null,"netIncome":null,"grossProfit":null,"operatingIncome":null,"freeCashFlow":null,"sharesOutstanding":null,"totalAssets":5940124.0,"totalLiabilities":11280510.0,"totalDebt":null,"cashAndEquivalents":226688.0,"stockholdersEquity":-5657996.0},{"date":"2019-03-31","revenue":212242.0,"eps":-0.05,"netIncome":-873317.0,"grossProfit":210743.0,"operatingIncome":-730566.0,"freeCashFlow":null,"sharesOutstanding":213926475.0,"totalAssets":7450191.0,"totalLiabilities":12976537.0,"totalDebt":null,"cashAndEquivalents":981341.0,"stockholdersEquity":-5762310.0},{"date":"2019-04-08","revenue":null,"eps":null,"netIncome":null,"grossProfit":null,"operatingIncome":null,"freeCashFlow":null,"sharesOutstanding":213926475.0,"totalAssets":null,"totalLiabilities":null,"totalDebt":null,"cashAndEquivalents":null,"stockholdersEquity":null},{"date":"2019-05-20","revenue":null,"eps":null,"netIncome":null,"grossProfit":null,"operatingIncome":null,"freeCashFlow":null,"sharesOutstanding":17694156.0,"totalAssets":null,"totalLiabilities":null,"totalDebt":null,"cashAndEquivalents":null,"stockholdersEquity":null},{"date":"2019-06-30","revenue":191782.0,"eps":-0.03,"netIncome":-614453.0,"grossProfit":178430.0,"operatingIncome":-488808.0,"freeCashFlow":null,"sharesOutstanding":18122860.0,"totalAssets":7140077.0,"totalLiabilities":10281505.0,"totalDebt":null,"cashAndEquivalents":540308.0,"stockholdersEquity":-3320515.0},{"date":"2019-08-07","revenue":null,"eps":null,"netIncome":null,"grossProfit":null,"operatingIncome":null,"freeCashFlow":null,"sharesOutstanding":18122860.0,"totalAssets":null,"totalLiabilities":null,"totalDebt":null,"cashAndEquivalents":null,"stockholdersEquity":null},{"date":"2019-09-30","revenue":197733.0,"eps":null,"netIncome":-1329685.0,"grossProfit":194936.0,"operatingIncome":-1115622.0,"freeCashFlow":null,"sharesOutstanding":null,"totalAssets":7404893.0,"totalLiabilities":6674702.0,"totalDebt":null,"cashAndEquivalents":1035678.0,"stockholdersEquity":665930.0},{"date":"2019-11-15","revenue":null,"eps":null,"netIncome":null,"grossProfit":null,"operatingIncome":null,"freeCashFlow":null,"sharesOutstanding":19478168.0,"totalAssets":null,"totalLiabilities":null,"totalDebt":null,"cashAndEquivalents":null,"stockholdersEquity":null},{"date":"2019-12-31","revenue":null,"eps":null,"netIncome":null,"grossProfit":null,"operatingIncome":null,"freeCashFlow":null,"sharesOutstanding":19478168.0,"totalAssets":6927811.0,"totalLiabilities":7052628.0,"totalDebt":null,"cashAndEquivalents":144295.0,"stockholdersEquity":-150964.0},{"date":"2020-03-31","revenue":78786.0,"eps":-0.06,"netIncome":-1309262.0,"grossProfit":74827.0,"operatingIncome":-1171377.0,"freeCashFlow":null,"sharesOutstanding":19488168.0,"totalAssets":6665209.0,"totalLiabilities":7837475.0,"totalDebt":null,"cashAndEquivalents":123645.0,"stockholdersEquity":-1136689.0},{"date":"2020-05-11","revenue":null,"eps":null,"netIncome":null,"grossProfit":null,"operatingIncome":null,"freeCashFlow":null,"sharesOutstanding":19488168.0,"totalAssets":null,"totalLiabilities":null,"totalDebt":null,"cashAndEquivalents":null,"stockholdersEquity":null},{"date":"2020-06-26","revenue":null,"eps":null,"netIncome":null,"grossProfit":null,"operatingIncome":null,"freeCashFlow":null,"sharesOutstanding":19488168.0,"totalAssets":null,"totalLiabilities":null,"totalDebt":null,"cashAndEquivalents":null,"stockholdersEquity":null},{"date":"2020-06-30","revenue":226513.0,"eps":-0.09,"netIncome":-2184057.0,"grossProfit":222277.0,"operatingIncome":-1194013.0,"freeCashFlow":null,"sharesOutstanding":19488168.0,"totalAssets":6432361.0,"totalLiabilities":7876386.0,"totalDebt":124400.0,"cashAndEquivalents":390221.0,"stockholdersEquity":-1073688.0},{"date":"2020-08-10","revenue":null,"eps":null,"netIncome":null,"grossProfit":null,"operatingIncome":null,"freeCashFlow":null,"sharesOutstanding":19538168.0,"totalAssets":null,"totalLiabilities":null,"totalDebt":null,"cashAndEquivalents":null,"stockholdersEquity":null},{"date":"2020-09-30","revenue":115553.0,"eps":-0.09,"netIncome":-2131131.0,"grossProfit":106934.0,"operatingIncome":-1289766.0,"freeCashFlow":null,"sharesOutstanding":20813903.0,"totalAssets":6529385.0,"totalLiabilities":7721225.0,"totalDebt":124400.0,"cashAndEquivalents":135705.0,"stockholdersEquity":-536418.0},{"date":"2020-11-12","revenue":null,"eps":null,"netIncome":null,"grossProfit":null,"operatingIncome":null,"freeCashFlow":null,"sharesOutstanding":20813903.0,"totalAssets":null,"totalLiabilities":null,"totalDebt":null,"cashAndEquivalents":null,"stockholdersEquity":null},{"date":"2020-12-31","revenue":null,"eps":null,"netIncome":null,"grossProfit":null,"operatingIncome":null,"freeCashFlow":null,"sharesOutstanding":null,"totalAssets":11606705.0,"totalLiabilities":8944638.0,"totalDebt":null,"cashAndEquivalents":4273208.0,"stockholdersEquity":3438340.0},{"date":"2021-03-15","revenue":null,"eps":null,"netIncome":null,"grossProfit":null,"operatingIncome":null,"freeCashFlow":null,"sharesOutstanding":24420526.0,"totalAssets":null,"totalLiabilities":null,"totalDebt":null,"cashAndEquivalents":null,"stockholdersEquity":null},{"date":"2021-03-31","revenue":263150.0,"eps":-0.05,"netIncome":-1195323.0,"grossProfit":261905.0,"operatingIncome":-1252745.0,"freeCashFlow":null,"sharesOutstanding":24420526.0,"totalAssets":10526062.0,"totalLiabilities":8797438.0,"totalDebt":null,"cashAndEquivalents":2615073.0,"stockholdersEquity":2571715.0},{"date":"2021-05-10","revenue":null,"eps":null,"netIncome":null,"grossProfit":null,"operatingIncome":null,"freeCashFlow":null,"sharesOutstanding":24420526.0,"totalAssets":null,"totalLiabilities":null,"totalDebt":null,"cashAndEquivalents":null,"stockholdersEquity":null},{"date":"2021-06-30","revenue":31441.0,"eps":-0.08,"netIncome":-1971566.0,"grossProfit":30795.0,"operatingIncome":-2035515.0,"freeCashFlow":null,"sharesOutstanding":24470526.0,"totalAssets":8944966.0,"totalLiabilities":8428977.0,"totalDebt":null,"cashAndEquivalents":924841.0,"stockholdersEquity":1440470.0},{"date":"2021-08-11","revenue":null,"eps":null,"netIncome":null,"grossProfit":null,"operatingIncome":null,"freeCashFlow":null,"sharesOutstanding":24470526.0,"totalAssets":null,"totalLiabilities":null,"totalDebt":null,"cashAndEquivalents":null,"stockholdersEquity":null},{"date":"2021-09-30","revenue":98999.0,"eps":-0.07,"netIncome":-1806488.0,"grossProfit":98606.0,"operatingIncome":-1970554.0,"freeCashFlow":null,"sharesOutstanding":28609388.0,"totalAssets":12354816.0,"totalLiabilities":4765075.0,"totalDebt":null,"cashAndEquivalents":3715609.0,"stockholdersEquity":8593978.0},{"date":"2021-11-12","revenue":null,"eps":null,"netIncome":null,"grossProfit":null,"operatingIncome":null,"freeCashFlow":null,"sharesOutstanding":28609388.0,"totalAssets":null,"totalLiabilities":null,"totalDebt":null,"cashAndEquivalents":null,"stockholdersEquity":null},{"date":"2021-12-31","revenue":null,"eps":null,"netIncome":null,"grossProfit":null,"operatingIncome":null,"freeCashFlow":null,"sharesOutstanding":null,"totalAssets":13698033.0,"totalLiabilities":4827691.0,"totalDebt":null,"cashAndEquivalents":5828548.0,"stockholdersEquity":8843653.0},{"date":"2022-03-30","revenue":null,"eps":null,"netIncome":null,"grossProfit":null,"operatingIncome":null,"freeCashFlow":null,"sharesOutstanding":30307329.0,"totalAssets":null,"totalLiabilities":null,"totalDebt":null,"cashAndEquivalents":null,"stockholdersEquity":null},{"date":"2022-03-31","revenue":25660.0,"eps":-0.2,"netIncome":-5995440.0,"grossProfit":23764.0,"operatingIncome":-6218721.0,"freeCashFlow":-3087477.0,"sharesOutstanding":null,"totalAssets":12066755.0,"totalLiabilities":4705364.0,"totalDebt":null,"cashAndEquivalents":2717936.0,"stockholdersEquity":7426877.0},{"date":"2022-05-16","revenue":null,"eps":null,"netIncome":null,"grossProfit":null,"operatingIncome":null,"freeCashFlow":null,"sharesOutstanding":32307329.0,"totalAssets":null,"totalLiabilities":null,"totalDebt":null,"cashAndEquivalents":null,"stockholdersEquity":null},{"date":"2022-06-30","revenue":312860.0,"eps":-0.59,"netIncome":-1858997.0,"grossProfit":304493.0,"operatingIncome":-2046860.0,"freeCashFlow":null,"sharesOutstanding":32632329.0,"totalAssets":13782612.0,"totalLiabilities":4602110.0,"totalDebt":null,"cashAndEquivalents":2910613.0,"stockholdersEquity":9334324.0},{"date":"2022-08-10","revenue":null,"eps":null,"netIncome":null,"grossProfit":null,"operatingIncome":null,"freeCashFlow":null,"sharesOutstanding":32632329.0,"totalAssets":null,"totalLiabilities":null,"totalDebt":null,"cashAndEquivalents":null,"stockholdersEquity":null},{"date":"2022-09-30","revenue":42269.0,"eps":-1.14,"netIncome":-3704864.0,"grossProfit":31528.0,"operatingIncome":-3715841.0,"freeCashFlow":null,"sharesOutstanding":32632329.0,"totalAssets":10480567.0,"totalLiabilities":4787368.0,"totalDebt":null,"cashAndEquivalents":1323543.0,"stockholdersEquity":5918681.0},{"date":"2022-11-11","revenue":null,"eps":null,"netIncome":null,"grossProfit":null,"operatingIncome":null,"freeCashFlow":null,"sharesOutstanding":32632329.0,"totalAssets":null,"totalLiabilities":null,"totalDebt":null,"cashAndEquivalents":null,"stockholdersEquity":null},{"date":"2022-12-31","revenue":null,"eps":null,"netIncome":null,"grossProfit":null,"operatingIncome":null,"freeCashFlow":null,"sharesOutstanding":null,"totalAssets":9579574.0,"totalLiabilities":6343435.0,"totalDebt":null,"cashAndEquivalents":85265.0,"stockholdersEquity":3098585.0},{"date":"2023-03-31","revenue":128272.0,"eps":-0.55,"netIncome":-1823695.0,"grossProfit":68036.0,"operatingIncome":-1906184.0,"freeCashFlow":null,"sharesOutstanding":33080740.0,"totalAssets":10734937.0,"totalLiabilities":9000430.0,"totalDebt":null,"cashAndEquivalents":1134959.0,"stockholdersEquity":1670488.0},{"date":"2023-05-11","revenue":null,"eps":null,"netIncome":null,"grossProfit":null,"operatingIncome":null,"freeCashFlow":null,"sharesOutstanding":33080740.0,"totalAssets":null,"totalLiabilities":null,"totalDebt":null,"cashAndEquivalents":null,"stockholdersEquity":null},{"date":"2023-06-30","revenue":6109.0,"eps":-0.68,"netIncome":-2263511.0,"grossProfit":-66872.0,"operatingIncome":-2193842.0,"freeCashFlow":null,"sharesOutstanding":3951388.0,"totalAssets":9320407.0,"totalLiabilities":9687417.0,"totalDebt":null,"cashAndEquivalents":99290.0,"stockholdersEquity":-379315.0},{"date":"2023-08-09","revenue":null,"eps":null,"netIncome":null,"grossProfit":null,"operatingIncome":null,"freeCashFlow":null,"sharesOutstanding":3951388.0,"totalAssets":null,"totalLiabilities":null,"totalDebt":null,"cashAndEquivalents":null,"stockholdersEquity":null},{"date":"2023-09-30","revenue":15884.0,"eps":-0.82,"netIncome":-3317516.0,"grossProfit":-13730.0,"operatingIncome":-2154873.0,"freeCashFlow":null,"sharesOutstanding":7231940.0,"totalAssets":16591507.0,"totalLiabilities":7529911.0,"totalDebt":null,"cashAndEquivalents":500069.0,"stockholdersEquity":9099855.0},{"date":"2023-11-09","revenue":null,"eps":null,"netIncome":null,"grossProfit":null,"operatingIncome":null,"freeCashFlow":null,"sharesOutstanding":7231940.0,"totalAssets":null,"totalLiabilities":null,"totalDebt":null,"cashAndEquivalents":null,"stockholdersEquity":null},{"date":"2023-12-31","revenue":null,"eps":null,"netIncome":null,"grossProfit":null,"operatingIncome":null,"freeCashFlow":null,"sharesOutstanding":null,"totalAssets":7784499.0,"totalLiabilities":6531026.0,"totalDebt":null,"cashAndEquivalents":60155.0,"stockholdersEquity":1554110.0},{"date":"2024-03-12","revenue":null,"eps":null,"netIncome":null,"grossProfit":null,"operatingIncome":null,"freeCashFlow":null,"sharesOutstanding":10560421.0,"totalAssets":null,"totalLiabilities":null,"totalDebt":null,"cashAndEquivalents":null,"stockholdersEquity":null},{"date":"2024-03-31","revenue":1205.0,"eps":-0.29,"netIncome":-2834199.0,"grossProfit":928.0,"operatingIncome":-2838255.0,"freeCashFlow":null,"sharesOutstanding":null,"totalAssets":7976010.0,"totalLiabilities":6517539.0,"totalDebt":null,"cashAndEquivalents":30489.0,"stockholdersEquity":1699551.0},{"date":"2024-05-10","revenue":null,"eps":null,"netIncome":null,"grossProfit":null,"operatingIncome":null,"freeCashFlow":null,"sharesOutstanding":10851823.0,"totalAssets":null,"totalLiabilities":null,"totalDebt":null,"cashAndEquivalents":null,"stockholdersEquity":null},{"date":"2024-06-30","revenue":117142.0,"eps":-0.08,"netIncome":-942336.0,"grossProfit":116952.0,"operatingIncome":-860107.0,"freeCashFlow":null,"sharesOutstanding":12421815.0,"totalAssets":8044434.0,"totalLiabilities":6504389.0,"totalDebt":null,"cashAndEquivalents":124296.0,"stockholdersEquity":1786202.0},{"date":"2024-08-14","revenue":null,"eps":null,"netIncome":null,"grossProfit":null,"operatingIncome":null,"freeCashFlow":null,"sharesOutstanding":12421815.0,"totalAssets":null,"totalLiabilities":null,"totalDebt":null,"cashAndEquivalents":null,"stockholdersEquity":null},{"date":"2024-09-30","revenue":389276.0,"eps":-0.03,"netIncome":-394769.0,"grossProfit":388980.0,"operatingIncome":-302316.0,"freeCashFlow":null,"sharesOutstanding":12975492.0,"totalAssets":7777705.0,"totalLiabilities":6440754.0,"totalDebt":null,"cashAndEquivalents":137344.0,"stockholdersEquity":1642038.0},{"date":"2024-11-13","revenue":null,"eps":null,"netIncome":null,"grossProfit":null,"operatingIncome":null,"freeCashFlow":null,"sharesOutstanding":12975492.0,"totalAssets":null,"totalLiabilities":null,"totalDebt":null,"cashAndEquivalents":null,"stockholdersEquity":null},{"date":"2024-12-31","revenue":null,"eps":null,"netIncome":null,"grossProfit":null,"operatingIncome":null,"freeCashFlow":null,"sharesOutstanding":null,"totalAssets":7539907.0,"totalLiabilities":6815948.0,"totalDebt":null,"cashAndEquivalents":248382.0,"stockholdersEquity":1226140.0},{"date":"2025-03-31","revenue":null,"eps":-0.06,"netIncome":-842075.0,"grossProfit":null,"operatingIncome":-693005.0,"freeCashFlow":null,"sharesOutstanding":15778305.0,"totalAssets":14875699.0,"totalLiabilities":6919404.0,"totalDebt":null,"cashAndEquivalents":152206.0,"stockholdersEquity":5404386.0},{"date":"2025-04-11","revenue":null,"eps":null,"netIncome":null,"grossProfit":null,"operatingIncome":null,"freeCashFlow":null,"sharesOutstanding":15778305.0,"totalAssets":null,"totalLiabilities":null,"totalDebt":null,"cashAndEquivalents":null,"stockholdersEquity":null},{"date":"2025-04-30","revenue":null,"eps":null,"netIncome":null,"grossProfit":null,"operatingIncome":null,"freeCashFlow":null,"sharesOutstanding":16773261.0,"totalAssets":null,"totalLiabilities":null,"totalDebt":null,"cashAndEquivalents":null,"stockholdersEquity":null},{"date":"2025-06-30","revenue":null,"eps":-0.13,"netIncome":-2257022.0,"grossProfit":null,"operatingIncome":-2294983.0,"freeCashFlow":null,"sharesOutstanding":23541824.0,"totalAssets":16241060.0,"totalLiabilities":6751327.0,"totalDebt":null,"cashAndEquivalents":388251.0,"stockholdersEquity":7013635.0},{"date":"2025-08-12","revenue":null,"eps":null,"netIncome":null,"grossProfit":null,"operatingIncome":null,"freeCashFlow":null,"sharesOutstanding":23541824.0,"totalAssets":null,"totalLiabilities":null,"totalDebt":null,"cashAndEquivalents":null,"stockholdersEquity":null},{"date":"2025-09-30","revenue":795950.0,"eps":-0.05,"netIncome":-1246513.0,"grossProfit":795950.0,"operatingIncome":-1168410.0,"freeCashFlow":null,"sharesOutstanding":24301089.0,"totalAssets":21176299.0,"totalLiabilities":6683592.0,"totalDebt":null,"cashAndEquivalents":192068.0,"stockholdersEquity":12057619.0},{"date":"2025-10-30","revenue":null,"eps":null,"netIncome":null,"grossProfit":null,"operatingIncome":null,"freeCashFlow":null,"sharesOutstanding":24301089.0,"totalAssets":null,"totalLiabilities":null,"totalDebt":null,"cashAndEquivalents":null,"stockholdersEquity":null},{"date":"2025-12-31","revenue":null,"eps":null,"netIncome":null,"grossProfit":null,"operatingIncome":null,"freeCashFlow":null,"sharesOutstanding":null,"totalAssets":21062203.0,"totalLiabilities":7764723.0,"totalDebt":null,"cashAndEquivalents":681480.0,"stockholdersEquity":11111861.0},{"date":"2026-03-03","revenue":null,"eps":null,"netIncome":null,"grossProfit":null,"operatingIncome":null,"freeCashFlow":null,"sharesOutstanding":25440407.0,"totalAssets":null,"totalLiabilities":null,"totalDebt":null,"cashAndEquivalents":null,"stockholdersEquity":null},{"date":"2026-03-31","revenue":null,"eps":null,"netIncome":null,"grossProfit":null,"operatingIncome":null,"freeCashFlow":null,"sharesOutstanding":25440407.0,"totalAssets":null,"totalLiabilities":null,"totalDebt":null,"cashAndEquivalents":null,"stockholdersEquity":null}]}