{"ticker":"LPBB","name":"Launch Two Acquisition Corp.","sector":null,"exchange":null,"quarters":[{"date":"2024-06-30","revenue":null,"eps":null,"netIncome":-39060.0,"grossProfit":null,"operatingIncome":-39060.0,"freeCashFlow":null,"sharesOutstanding":null,"totalAssets":null,"totalLiabilities":null,"totalDebt":null,"cashAndEquivalents":null,"stockholdersEquity":-14060.0},{"date":"2024-09-30","revenue":null,"eps":null,"netIncome":-16084.0,"grossProfit":null,"operatingIncome":-16084.0,"freeCashFlow":null,"sharesOutstanding":null,"totalAssets":528939.0,"totalLiabilities":559083.0,"totalDebt":null,"cashAndEquivalents":null,"stockholdersEquity":-30144.0},{"date":"2024-12-31","revenue":null,"eps":null,"netIncome":null,"grossProfit":null,"operatingIncome":null,"freeCashFlow":null,"sharesOutstanding":null,"totalAssets":234741199.0,"totalLiabilities":11041136.0,"totalDebt":null,"cashAndEquivalents":null,"stockholdersEquity":-9838276.0},{"date":"2025-03-31","revenue":null,"eps":null,"netIncome":2215852.0,"grossProfit":null,"operatingIncome":-207897.0,"freeCashFlow":null,"sharesOutstanding":null,"totalAssets":237022302.0,"totalLiabilities":11106387.0,"totalDebt":null,"cashAndEquivalents":null,"stockholdersEquity":-10045949.0},{"date":"2025-06-30","revenue":null,"eps":null,"netIncome":2367013.0,"grossProfit":null,"operatingIncome":-175476.0,"freeCashFlow":null,"sharesOutstanding":null,"totalAssets":239314095.0,"totalLiabilities":11031167.0,"totalDebt":null,"cashAndEquivalents":null,"stockholdersEquity":-10221238.0},{"date":"2025-09-30","revenue":null,"eps":null,"netIncome":2268915.0,"grossProfit":null,"operatingIncome":-238860.0,"freeCashFlow":null,"sharesOutstanding":null,"totalAssets":241658082.0,"totalLiabilities":11106239.0,"totalDebt":null,"cashAndEquivalents":null,"stockholdersEquity":-10459946.0}]}