{"ticker":"SAIL","name":"SailPoint, Inc.","sector":null,"exchange":null,"quarters":[{"date":"2023-12-31","revenue":null,"eps":null,"netIncome":null,"grossProfit":null,"operatingIncome":null,"freeCashFlow":null,"sharesOutstanding":null,"totalAssets":null,"totalLiabilities":null,"totalDebt":null,"cashAndEquivalents":null,"stockholdersEquity":-541195000.0},{"date":"2024-01-31","revenue":null,"eps":null,"netIncome":null,"grossProfit":null,"operatingIncome":null,"freeCashFlow":null,"sharesOutstanding":null,"totalAssets":null,"totalLiabilities":null,"totalDebt":null,"cashAndEquivalents":null,"stockholdersEquity":-541195000.0},{"date":"2024-03-31","revenue":187656000.0,"eps":-0.77,"netIncome":-89176000.0,"grossProfit":115490000.0,"operatingIncome":-68193000.0,"freeCashFlow":-55973000.0,"sharesOutstanding":null,"totalAssets":null,"totalLiabilities":null,"totalDebt":null,"cashAndEquivalents":146750000.0,"stockholdersEquity":-622527000.0},{"date":"2024-04-30","revenue":187656000.0,"eps":-0.77,"netIncome":-89176000.0,"grossProfit":115490000.0,"operatingIncome":-68193000.0,"freeCashFlow":-55973000.0,"sharesOutstanding":null,"totalAssets":null,"totalLiabilities":null,"totalDebt":null,"cashAndEquivalents":146750000.0,"stockholdersEquity":-622527000.0},{"date":"2024-06-30","revenue":198575000.0,"eps":-2.97,"netIncome":-87130000.0,"grossProfit":123313000.0,"operatingIncome":-65830000.0,"freeCashFlow":null,"sharesOutstanding":null,"totalAssets":null,"totalLiabilities":null,"totalDebt":null,"cashAndEquivalents":89690000.0,"stockholdersEquity":-701320000.0},{"date":"2024-07-31","revenue":198575000.0,"eps":-2.97,"netIncome":-87130000.0,"grossProfit":123313000.0,"operatingIncome":-65830000.0,"freeCashFlow":null,"sharesOutstanding":null,"totalAssets":null,"totalLiabilities":null,"totalDebt":null,"cashAndEquivalents":89690000.0,"stockholdersEquity":-701320000.0},{"date":"2024-09-30","revenue":235259000.0,"eps":-2.67,"netIncome":-59420000.0,"grossProfit":157303000.0,"operatingIncome":-24497000.0,"freeCashFlow":null,"sharesOutstanding":null,"totalAssets":null,"totalLiabilities":null,"totalDebt":null,"cashAndEquivalents":68166000.0,"stockholdersEquity":-754144000.0},{"date":"2024-10-31","revenue":235259000.0,"eps":-2.67,"netIncome":-59420000.0,"grossProfit":157303000.0,"operatingIncome":-24497000.0,"freeCashFlow":null,"sharesOutstanding":null,"totalAssets":null,"totalLiabilities":null,"totalDebt":null,"cashAndEquivalents":68166000.0,"stockholdersEquity":-754144000.0},{"date":"2024-12-31","revenue":null,"eps":null,"netIncome":null,"grossProfit":null,"operatingIncome":null,"freeCashFlow":null,"sharesOutstanding":null,"totalAssets":7411916000.0,"totalLiabilities":1804215000.0,"totalDebt":1024467000.0,"cashAndEquivalents":121293000.0,"stockholdersEquity":-5588440000.0},{"date":"2025-01-31","revenue":null,"eps":null,"netIncome":null,"grossProfit":null,"operatingIncome":null,"freeCashFlow":null,"sharesOutstanding":null,"totalAssets":7411916000.0,"totalLiabilities":1804215000.0,"totalDebt":1024467000.0,"cashAndEquivalents":121293000.0,"stockholdersEquity":-5588440000.0},{"date":"2025-03-31","revenue":230468000.0,"eps":-0.42,"netIncome":-187312000.0,"grossProfit":127655000.0,"operatingIncome":-184965000.0,"freeCashFlow":-98998000.0,"sharesOutstanding":null,"totalAssets":7414478000.0,"totalLiabilities":636695000.0,"totalDebt":0.0,"cashAndEquivalents":228117000.0,"stockholdersEquity":6777783000.0},{"date":"2025-04-30","revenue":230468000.0,"eps":-0.42,"netIncome":-187312000.0,"grossProfit":127655000.0,"operatingIncome":-184965000.0,"freeCashFlow":-98998000.0,"sharesOutstanding":null,"totalAssets":7414478000.0,"totalLiabilities":636695000.0,"totalDebt":0.0,"cashAndEquivalents":228117000.0,"stockholdersEquity":6777783000.0},{"date":"2025-06-06","revenue":null,"eps":null,"netIncome":null,"grossProfit":null,"operatingIncome":null,"freeCashFlow":null,"sharesOutstanding":556588850.0,"totalAssets":null,"totalLiabilities":null,"totalDebt":null,"cashAndEquivalents":null,"stockholdersEquity":null},{"date":"2025-06-30","revenue":264359000.0,"eps":-0.02,"netIncome":-10552000.0,"grossProfit":177806000.0,"operatingIncome":-40798000.0,"freeCashFlow":null,"sharesOutstanding":556588850.0,"totalAssets":7445941000.0,"totalLiabilities":629795000.0,"totalDebt":0.0,"cashAndEquivalents":271052000.0,"stockholdersEquity":6816146000.0},{"date":"2025-07-31","revenue":264359000.0,"eps":-0.02,"netIncome":-10552000.0,"grossProfit":177806000.0,"operatingIncome":-40798000.0,"freeCashFlow":null,"sharesOutstanding":null,"totalAssets":7445941000.0,"totalLiabilities":629795000.0,"totalDebt":0.0,"cashAndEquivalents":271052000.0,"stockholdersEquity":6816146000.0},{"date":"2025-09-05","revenue":null,"eps":null,"netIncome":null,"grossProfit":null,"operatingIncome":null,"freeCashFlow":null,"sharesOutstanding":556635292.0,"totalAssets":null,"totalLiabilities":null,"totalDebt":null,"cashAndEquivalents":null,"stockholdersEquity":null},{"date":"2025-09-30","revenue":281942000.0,"eps":-0.06,"netIncome":-35975000.0,"grossProfit":187048000.0,"operatingIncome":-41622000.0,"freeCashFlow":null,"sharesOutstanding":556635292.0,"totalAssets":7474805000.0,"totalLiabilities":645215000.0,"totalDebt":0.0,"cashAndEquivalents":298114000.0,"stockholdersEquity":6829590000.0},{"date":"2025-10-31","revenue":281942000.0,"eps":-0.06,"netIncome":-35975000.0,"grossProfit":187048000.0,"operatingIncome":-41622000.0,"freeCashFlow":null,"sharesOutstanding":null,"totalAssets":7474805000.0,"totalLiabilities":645215000.0,"totalDebt":0.0,"cashAndEquivalents":298114000.0,"stockholdersEquity":6829590000.0},{"date":"2025-12-05","revenue":null,"eps":null,"netIncome":null,"grossProfit":null,"operatingIncome":null,"freeCashFlow":null,"sharesOutstanding":561625760.0,"totalAssets":null,"totalLiabilities":null,"totalDebt":null,"cashAndEquivalents":null,"stockholdersEquity":null},{"date":"2025-12-31","revenue":null,"eps":null,"netIncome":null,"grossProfit":null,"operatingIncome":null,"freeCashFlow":null,"sharesOutstanding":561625760.0,"totalAssets":null,"totalLiabilities":null,"totalDebt":null,"cashAndEquivalents":null,"stockholdersEquity":null}]}