{"ticker":"TRMB","name":"TRIMBLE INC.","sector":null,"exchange":null,"quarters":[{"date":"2011-03-31","revenue":384000000.0,"eps":0.16,"netIncome":40000000.0,"grossProfit":191530000.0,"operatingIncome":43675000.0,"freeCashFlow":23891000.0,"sharesOutstanding":122171485.0,"totalAssets":1999704000.0,"totalLiabilities":510703000.0,"totalDebt":null,"cashAndEquivalents":244342000.0,"stockholdersEquity":1470289000.0},{"date":"2011-06-30","revenue":407000000.0,"eps":0.22,"netIncome":54000000.0,"grossProfit":208734000.0,"operatingIncome":95242000.0,"freeCashFlow":101394000.0,"sharesOutstanding":122799179.0,"totalAssets":2069805000.0,"totalLiabilities":509803000.0,"totalDebt":127256000.0,"cashAndEquivalents":249811000.0,"stockholdersEquity":1541349000.0},{"date":"2011-09-30","revenue":417000000.0,"eps":0.11,"netIncome":28000000.0,"grossProfit":211559000.0,"operatingIncome":127690000.0,"freeCashFlow":145819000.0,"sharesOutstanding":123311005.0,"totalAssets":2713398000.0,"totalLiabilities":1148941000.0,"totalDebt":637253000.0,"cashAndEquivalents":138255000.0,"stockholdersEquity":1544109000.0},{"date":"2011-12-31","revenue":435000000.0,"eps":0.12,"netIncome":29000000.0,"grossProfit":217758000.0,"operatingIncome":null,"freeCashFlow":null,"sharesOutstanding":null,"totalAssets":2652475000.0,"totalLiabilities":1063573000.0,"totalDebt":564436000.0,"cashAndEquivalents":154621000.0,"stockholdersEquity":1569293000.0},{"date":"2012-03-31","revenue":502000000.0,"eps":0.2,"netIncome":51000000.0,"grossProfit":259150000.0,"operatingIncome":59848000.0,"freeCashFlow":60014000.0,"sharesOutstanding":124408085.0,"totalAssets":2872072000.0,"totalLiabilities":1168516000.0,"totalDebt":623133000.0,"cashAndEquivalents":209146000.0,"stockholdersEquity":1687058000.0},{"date":"2012-06-30","revenue":518000000.0,"eps":0.21,"netIncome":54000000.0,"grossProfit":267696000.0,"operatingIncome":118769000.0,"freeCashFlow":133786000.0,"sharesOutstanding":125693020.0,"totalAssets":2972962000.0,"totalLiabilities":1250225000.0,"totalDebt":697357000.0,"cashAndEquivalents":121937000.0,"stockholdersEquity":1706766000.0},{"date":"2012-09-30","revenue":505000000.0,"eps":0.21,"netIncome":53000000.0,"grossProfit":262867000.0,"operatingIncome":182239000.0,"freeCashFlow":209768000.0,"sharesOutstanding":126186330.0,"totalAssets":3021493000.0,"totalLiabilities":1196440000.0,"totalDebt":643107000.0,"cashAndEquivalents":141840000.0,"stockholdersEquity":1808630000.0},{"date":"2012-12-31","revenue":516000000.0,"eps":0.12,"netIncome":33000000.0,"grossProfit":256463000.0,"operatingIncome":null,"freeCashFlow":null,"sharesOutstanding":null,"totalAssets":3469104000.0,"totalLiabilities":1555580000.0,"totalDebt":911158000.0,"cashAndEquivalents":157800000.0,"stockholdersEquity":1897455000.0},{"date":"2013-03-31","revenue":556000000.0,"eps":0.19,"netIncome":50000000.0,"grossProfit":286914000.0,"operatingIncome":56457000.0,"freeCashFlow":22461000.0,"sharesOutstanding":127657269.0,"totalAssets":3565721000.0,"totalLiabilities":1599853000.0,"totalDebt":920439000.0,"cashAndEquivalents":143552000.0,"stockholdersEquity":1949793000.0},{"date":"2013-06-30","revenue":576000000.0,"eps":0.21,"netIncome":55000000.0,"grossProfit":302401000.0,"operatingIncome":121362000.0,"freeCashFlow":132612000.0,"sharesOutstanding":256721284.0,"totalAssets":3633760000.0,"totalLiabilities":1592471000.0,"totalDebt":899187000.0,"cashAndEquivalents":129072000.0,"stockholdersEquity":2023873000.0},{"date":"2013-09-30","revenue":557000000.0,"eps":0.21,"netIncome":54000000.0,"grossProfit":295053000.0,"operatingIncome":184391000.0,"freeCashFlow":220762000.0,"sharesOutstanding":257841947.0,"totalAssets":3635172000.0,"totalLiabilities":1495019000.0,"totalDebt":809064000.0,"cashAndEquivalents":115257000.0,"stockholdersEquity":2126819000.0},{"date":"2013-12-31","revenue":599000000.0,"eps":0.23,"netIncome":60000000.0,"grossProfit":319454000.0,"operatingIncome":null,"freeCashFlow":null,"sharesOutstanding":null,"totalAssets":3700840000.0,"totalLiabilities":1466858000.0,"totalDebt":758458000.0,"cashAndEquivalents":147200000.0,"stockholdersEquity":2220906000.0},{"date":"2014-03-31","revenue":605000000.0,"eps":0.26,"netIncome":69000000.0,"grossProfit":326900000.0,"operatingIncome":75700000.0,"freeCashFlow":69795000.0,"sharesOutstanding":259844137.0,"totalAssets":3777583000.0,"totalLiabilities":1424032000.0,"totalDebt":664652000.0,"cashAndEquivalents":165200000.0,"stockholdersEquity":2342013000.0},{"date":"2014-06-30","revenue":642000000.0,"eps":0.29,"netIncome":78000000.0,"grossProfit":354600000.0,"operatingIncome":172900000.0,"freeCashFlow":null,"sharesOutstanding":259914767.0,"totalAssets":3867239000.0,"totalLiabilities":1416444000.0,"totalDebt":655863000.0,"cashAndEquivalents":278900000.0,"stockholdersEquity":2439064000.0},{"date":"2014-09-30","revenue":585000000.0,"eps":0.04,"netIncome":12000000.0,"grossProfit":316800000.0,"operatingIncome":184000000.0,"freeCashFlow":null,"sharesOutstanding":259006068.0,"totalAssets":3819374000.0,"totalLiabilities":1455705000.0,"totalDebt":646739000.0,"cashAndEquivalents":139500000.0,"stockholdersEquity":2351865000.0},{"date":"2014-12-31","revenue":564000000.0,"eps":0.22,"netIncome":56000000.0,"grossProfit":292500000.0,"operatingIncome":null,"freeCashFlow":null,"sharesOutstanding":null,"totalAssets":3855900000.0,"totalLiabilities":1502500000.0,"totalDebt":735400000.0,"cashAndEquivalents":148000000.0,"stockholdersEquity":2341600000.0},{"date":"2015-03-31","revenue":583000000.0,"eps":0.13,"netIncome":34000000.0,"grossProfit":307200000.0,"operatingIncome":39500000.0,"freeCashFlow":null,"sharesOutstanding":259176857.0,"totalAssets":3797700000.0,"totalLiabilities":1457100000.0,"totalDebt":663400000.0,"cashAndEquivalents":145700000.0,"stockholdersEquity":2339400000.0},{"date":"2015-06-30","revenue":586000000.0,"eps":0.1,"netIncome":26000000.0,"grossProfit":303900000.0,"operatingIncome":75500000.0,"freeCashFlow":null,"sharesOutstanding":257048584.0,"totalAssets":3780200000.0,"totalLiabilities":1441000000.0,"totalDebt":639600000.0,"cashAndEquivalents":129000000.0,"stockholdersEquity":2338100000.0},{"date":"2015-09-30","revenue":562000000.0,"eps":0.14,"netIncome":37000000.0,"grossProfit":298000000.0,"operatingIncome":121500000.0,"freeCashFlow":null,"sharesOutstanding":250481619.0,"totalAssets":3719900000.0,"totalLiabilities":1516700000.0,"totalDebt":759400000.0,"cashAndEquivalents":123600000.0,"stockholdersEquity":2202200000.0},{"date":"2015-12-31","revenue":560000000.0,"eps":0.1,"netIncome":24000000.0,"grossProfit":293100000.0,"operatingIncome":null,"freeCashFlow":null,"sharesOutstanding":null,"totalAssets":3680700000.0,"totalLiabilities":1460100000.0,"totalDebt":729700000.0,"cashAndEquivalents":116000000.0,"stockholdersEquity":2219700000.0},{"date":"2016-03-31","revenue":583000000.0,"eps":0.08,"netIncome":20000000.0,"grossProfit":324300000.0,"operatingIncome":29900000.0,"freeCashFlow":null,"sharesOutstanding":250900362.0,"totalAssets":3749900000.0,"totalLiabilities":1463200000.0,"totalDebt":674900000.0,"cashAndEquivalents":174700000.0,"stockholdersEquity":2285900000.0},{"date":"2016-06-30","revenue":610000000.0,"eps":0.14,"netIncome":36000000.0,"grossProfit":342600000.0,"operatingIncome":70400000.0,"freeCashFlow":null,"sharesOutstanding":249174915.0,"totalAssets":3751600000.0,"totalLiabilities":1506900000.0,"totalDebt":725000000.0,"cashAndEquivalents":231900000.0,"stockholdersEquity":2244800000.0},{"date":"2016-09-30","revenue":584000000.0,"eps":0.15,"netIncome":39000000.0,"grossProfit":351200000.0,"operatingIncome":125700000.0,"freeCashFlow":null,"sharesOutstanding":250583803.0,"totalAssets":3731400000.0,"totalLiabilities":1411700000.0,"totalDebt":669800000.0,"cashAndEquivalents":213500000.0,"stockholdersEquity":2319900000.0},{"date":"2016-12-31","revenue":585000000.0,"eps":0.15,"netIncome":38000000.0,"grossProfit":359500000.0,"operatingIncome":null,"freeCashFlow":null,"sharesOutstanding":null,"totalAssets":3673800000.0,"totalLiabilities":1368100000.0,"totalDebt":619900000.0,"cashAndEquivalents":216100000.0,"stockholdersEquity":2305800000.0},{"date":"2017-03-31","revenue":611000000.0,"eps":0.19,"netIncome":50000000.0,"grossProfit":396200000.0,"operatingIncome":54700000.0,"freeCashFlow":null,"sharesOutstanding":252283685.0,"totalAssets":3897400000.0,"totalLiabilities":1476500000.0,"totalDebt":648100000.0,"cashAndEquivalents":280800000.0,"stockholdersEquity":2421000000.0},{"date":"2017-06-30","revenue":660000000.0,"eps":0.18,"netIncome":47000000.0,"grossProfit":422700000.0,"operatingIncome":113700000.0,"freeCashFlow":null,"sharesOutstanding":253150381.0,"totalAssets":4038300000.0,"totalLiabilities":1520600000.0,"totalDebt":612300000.0,"cashAndEquivalents":384900000.0,"stockholdersEquity":2517800000.0},{"date":"2017-09-30","revenue":676000000.0,"eps":0.22,"netIncome":57000000.0,"grossProfit":426900000.0,"operatingIncome":180000000.0,"freeCashFlow":null,"sharesOutstanding":251761300.0,"totalAssets":4180700000.0,"totalLiabilities":1623300000.0,"totalDebt":695800000.0,"cashAndEquivalents":255000000.0,"stockholdersEquity":2557500000.0},{"date":"2017-12-31","revenue":700000000.0,"eps":-0.13,"netIncome":-36000000.0,"grossProfit":435200000.0,"operatingIncome":null,"freeCashFlow":null,"sharesOutstanding":null,"totalAssets":4316300000.0,"totalLiabilities":1901800000.0,"totalDebt":913900000.0,"cashAndEquivalents":358500000.0,"stockholdersEquity":2414500000.0},{"date":"2018-03-31","revenue":742000000.0,"eps":0.23,"netIncome":59000000.0,"grossProfit":396200000.0,"operatingIncome":64200000.0,"freeCashFlow":null,"sharesOutstanding":248266451.0,"totalAssets":4673700000.0,"totalLiabilities":2173800000.0,"totalDebt":1122300000.0,"cashAndEquivalents":274500000.0,"stockholdersEquity":2499700000.0},{"date":"2018-06-30","revenue":786000000.0,"eps":0.25,"netIncome":64000000.0,"grossProfit":422700000.0,"operatingIncome":153700000.0,"freeCashFlow":null,"sharesOutstanding":249956293.0,"totalAssets":4858300000.0,"totalLiabilities":2340700000.0,"totalDebt":1286600000.0,"cashAndEquivalents":571000000.0,"stockholdersEquity":2517400000.0},{"date":"2018-09-30","revenue":795000000.0,"eps":0.29,"netIncome":74000000.0,"grossProfit":426900000.0,"operatingIncome":231100000.0,"freeCashFlow":331700000.0,"sharesOutstanding":251146789.0,"totalAssets":5782200000.0,"totalLiabilities":3133600000.0,"totalDebt":2012700000.0,"cashAndEquivalents":205400000.0,"stockholdersEquity":2648400000.0},{"date":"2018-12-31","revenue":786000000.0,"eps":0.35,"netIncome":87000000.0,"grossProfit":435200000.0,"operatingIncome":null,"freeCashFlow":null,"sharesOutstanding":null,"totalAssets":5776400000.0,"totalLiabilities":3101600000.0,"totalDebt":1968500000.0,"cashAndEquivalents":172500000.0,"stockholdersEquity":2674400000.0},{"date":"2019-03-31","revenue":802000000.0,"eps":0.25,"netIncome":62000000.0,"grossProfit":438300000.0,"operatingIncome":86300000.0,"freeCashFlow":133100000.0,"sharesOutstanding":251514221.0,"totalAssets":5920100000.0,"totalLiabilities":3177100000.0,"totalDebt":1894600000.0,"cashAndEquivalents":216700000.0,"stockholdersEquity":2741700000.0},{"date":"2019-06-30","revenue":855000000.0,"eps":0.37,"netIncome":95000000.0,"grossProfit":898900000.0,"operatingIncome":196000000.0,"freeCashFlow":287000000.0,"sharesOutstanding":251789878.0,"totalAssets":5876100000.0,"totalLiabilities":3050800000.0,"totalDebt":1742900000.0,"cashAndEquivalents":199600000.0,"stockholdersEquity":2824000000.0},{"date":"2019-09-30","revenue":784000000.0,"eps":0.31,"netIncome":78000000.0,"grossProfit":1320900000.0,"operatingIncome":287700000.0,"freeCashFlow":408200000.0,"sharesOutstanding":249133702.0,"totalAssets":5803900000.0,"totalLiabilities":3015800000.0,"totalDebt":1750300000.0,"cashAndEquivalents":184600000.0,"stockholdersEquity":2786800000.0},{"date":"2019-12-31","revenue":824000000.0,"eps":1.1,"netIncome":279000000.0,"grossProfit":460000000.0,"operatingIncome":null,"freeCashFlow":null,"sharesOutstanding":null,"totalAssets":6640700000.0,"totalLiabilities":3520300000.0,"totalDebt":1624200000.0,"cashAndEquivalents":189200000.0,"stockholdersEquity":3119000000.0},{"date":"2020-03-31","revenue":792000000.0,"eps":0.25,"netIncome":62000000.0,"grossProfit":441000000.0,"operatingIncome":98300000.0,"freeCashFlow":139000000.0,"sharesOutstanding":250166168.0,"totalAssets":6705700000.0,"totalLiabilities":3603400000.0,"totalDebt":1975400000.0,"cashAndEquivalents":216800000.0,"stockholdersEquity":3101300000.0},{"date":"2020-06-30","revenue":734000000.0,"eps":0.25,"netIncome":63000000.0,"grossProfit":846700000.0,"operatingIncome":195900000.0,"freeCashFlow":273600000.0,"sharesOutstanding":250215769.0,"totalAssets":6645000000.0,"totalLiabilities":3431900000.0,"totalDebt":1832700000.0,"cashAndEquivalents":196400000.0,"stockholdersEquity":3211900000.0},{"date":"2020-09-30","revenue":792000000.0,"eps":0.34,"netIncome":85000000.0,"grossProfit":1286400000.0,"operatingIncome":297900000.0,"freeCashFlow":438600000.0,"sharesOutstanding":250175639.0,"totalAssets":6624300000.0,"totalLiabilities":3273000000.0,"totalDebt":1390600000.0,"cashAndEquivalents":184000000.0,"stockholdersEquity":3350000000.0},{"date":"2020-12-31","revenue":830000000.0,"eps":0.71,"netIncome":180000000.0,"grossProfit":null,"operatingIncome":null,"freeCashFlow":null,"sharesOutstanding":null,"totalAssets":6876900000.0,"totalLiabilities":3278300000.0,"totalDebt":1291400000.0,"cashAndEquivalents":237700000.0,"stockholdersEquity":3598600000.0},{"date":"2021-03-31","revenue":887000000.0,"eps":0.45,"netIncome":115000000.0,"grossProfit":493300000.0,"operatingIncome":140900000.0,"freeCashFlow":217600000.0,"sharesOutstanding":250974620.0,"totalAssets":6780500000.0,"totalLiabilities":3106900000.0,"totalDebt":1291900000.0,"cashAndEquivalents":264600000.0,"stockholdersEquity":3673600000.0},{"date":"2021-06-30","revenue":945000000.0,"eps":0.55,"netIncome":139000000.0,"grossProfit":1018700000.0,"operatingIncome":285700000.0,"freeCashFlow":407400000.0,"sharesOutstanding":251619889.0,"totalAssets":6962200000.0,"totalLiabilities":3123600000.0,"totalDebt":1292300000.0,"cashAndEquivalents":484400000.0,"stockholdersEquity":3838600000.0},{"date":"2021-09-30","revenue":901000000.0,"eps":0.49,"netIncome":124000000.0,"grossProfit":1523200000.0,"operatingIncome":433200000.0,"freeCashFlow":563800000.0,"sharesOutstanding":251008389.0,"totalAssets":7003400000.0,"totalLiabilities":3121600000.0,"totalDebt":1292800000.0,"cashAndEquivalents":513200000.0,"stockholdersEquity":3881800000.0},{"date":"2021-12-31","revenue":926000000.0,"eps":0.45,"netIncome":115000000.0,"grossProfit":null,"operatingIncome":null,"freeCashFlow":null,"sharesOutstanding":null,"totalAssets":7099600000.0,"totalLiabilities":3154900000.0,"totalDebt":1293200000.0,"cashAndEquivalents":325700000.0,"stockholdersEquity":3944700000.0},{"date":"2022-03-31","revenue":994000000.0,"eps":0.44,"netIncome":110000000.0,"grossProfit":549600000.0,"operatingIncome":156900000.0,"freeCashFlow":138500000.0,"sharesOutstanding":251215563.0,"totalAssets":7177400000.0,"totalLiabilities":3189500000.0,"totalDebt":1293700000.0,"cashAndEquivalents":357200000.0,"stockholdersEquity":3987900000.0},{"date":"2022-06-30","revenue":941000000.0,"eps":0.67,"netIncome":168000000.0,"grossProfit":1087100000.0,"operatingIncome":291800000.0,"freeCashFlow":173300000.0,"sharesOutstanding":247657418.0,"totalAssets":6919500000.0,"totalLiabilities":3025000000.0,"totalDebt":null,"cashAndEquivalents":350100000.0,"stockholdersEquity":3894500000.0},{"date":"2022-09-30","revenue":885000000.0,"eps":0.34,"netIncome":86000000.0,"grossProfit":1602500000.0,"operatingIncome":414200000.0,"freeCashFlow":248500000.0,"sharesOutstanding":246624691.0,"totalAssets":7077700000.0,"totalLiabilities":3232900000.0,"totalDebt":null,"cashAndEquivalents":308700000.0,"stockholdersEquity":3844800000.0},{"date":"2022-12-31","revenue":857000000.0,"eps":0.35,"netIncome":86000000.0,"grossProfit":null,"operatingIncome":null,"freeCashFlow":null,"sharesOutstanding":246951697.0,"totalAssets":7269000000.0,"totalLiabilities":3218800000.0,"totalDebt":1220000000.0,"cashAndEquivalents":271000000.0,"stockholdersEquity":4050200000.0},{"date":"2023-03-31","revenue":915000000.0,"eps":0.52,"netIncome":129000000.0,"grossProfit":560800000.0,"operatingIncome":137000000.0,"freeCashFlow":202300000.0,"sharesOutstanding":247746800.0,"totalAssets":8012900000.0,"totalLiabilities":3767700000.0,"totalDebt":null,"cashAndEquivalents":1038100000.0,"stockholdersEquity":4245200000.0},{"date":"2023-06-30","revenue":994000000.0,"eps":0.18,"netIncome":45000000.0,"grossProfit":1165300000.0,"operatingIncome":230600000.0,"freeCashFlow":332100000.0,"sharesOutstanding":248321667.0,"totalAssets":9556300000.0,"totalLiabilities":5225000000.0,"totalDebt":null,"cashAndEquivalents":237300000.0,"stockholdersEquity":4331300000.0},{"date":"2023-09-30","revenue":957000000.0,"eps":0.3,"netIncome":75000000.0,"grossProfit":1755500000.0,"operatingIncome":351900000.0,"freeCashFlow":466000000.0,"sharesOutstanding":248767565.0,"totalAssets":9330700000.0,"totalLiabilities":4987700000.0,"totalDebt":null,"cashAndEquivalents":216800000.0,"stockholdersEquity":4343000000.0},{"date":"2023-12-31","revenue":932000000.0,"eps":0.25,"netIncome":63000000.0,"grossProfit":null,"operatingIncome":null,"freeCashFlow":null,"sharesOutstanding":null,"totalAssets":9539300000.0,"totalLiabilities":5039200000.0,"totalDebt":null,"cashAndEquivalents":229800000.0,"stockholdersEquity":4500100000.0},{"date":"2024-03-31","revenue":953000000.0,"eps":0.23,"netIncome":57000000.0,"grossProfit":593600000.0,"operatingIncome":109200000.0,"freeCashFlow":227000000.0,"sharesOutstanding":245687181.0,"totalAssets":9321200000.0,"totalLiabilities":4972100000.0,"totalDebt":null,"cashAndEquivalents":255100000.0,"stockholdersEquity":4349100000.0},{"date":"2024-06-30","revenue":871000000.0,"eps":5.34,"netIncome":1316000000.0,"grossProfit":1139500000.0,"operatingIncome":170800000.0,"freeCashFlow":300300000.0,"sharesOutstanding":null,"totalAssets":9597800000.0,"totalLiabilities":3964400000.0,"totalDebt":null,"cashAndEquivalents":944100000.0,"stockholdersEquity":5633400000.0},{"date":"2024-09-30","revenue":876000000.0,"eps":0.16,"netIncome":41000000.0,"grossProfit":1715100000.0,"operatingIncome":287200000.0,"freeCashFlow":388800000.0,"sharesOutstanding":null,"totalAssets":9866700000.0,"totalLiabilities":3991600000.0,"totalDebt":null,"cashAndEquivalents":1036900000.0,"stockholdersEquity":5875100000.0},{"date":"2024-12-31","revenue":983000000.0,"eps":0.36,"netIncome":90000000.0,"grossProfit":null,"operatingIncome":null,"freeCashFlow":null,"sharesOutstanding":245792054.0,"totalAssets":9488300000.0,"totalLiabilities":3743000000.0,"totalDebt":1390600000.0,"cashAndEquivalents":738800000.0,"stockholdersEquity":5745300000.0},{"date":"2025-03-31","revenue":841000000.0,"eps":0.27,"netIncome":67000000.0,"grossProfit":560800000.0,"operatingIncome":97500000.0,"freeCashFlow":149000000.0,"sharesOutstanding":238583485.0,"totalAssets":8898900000.0,"totalLiabilities":3479800000.0,"totalDebt":null,"cashAndEquivalents":290000000.0,"stockholdersEquity":5419100000.0},{"date":"2025-06-30","revenue":876000000.0,"eps":0.37,"netIncome":89000000.0,"grossProfit":1158700000.0,"operatingIncome":225300000.0,"freeCashFlow":89600000.0,"sharesOutstanding":237969093.0,"totalAssets":9099200000.0,"totalLiabilities":3411100000.0,"totalDebt":null,"cashAndEquivalents":265900000.0,"stockholdersEquity":5688100000.0},{"date":"2025-09-30","revenue":901000000.0,"eps":0.46,"netIncome":112000000.0,"grossProfit":1779800000.0,"operatingIncome":375800000.0,"freeCashFlow":206200000.0,"sharesOutstanding":237920962.0,"totalAssets":9019600000.0,"totalLiabilities":3229600000.0,"totalDebt":1391800000.0,"cashAndEquivalents":232700000.0,"stockholdersEquity":5790000000.0},{"date":"2025-12-31","revenue":970000000.0,"eps":0.65,"netIncome":157000000.0,"grossProfit":null,"operatingIncome":null,"freeCashFlow":null,"sharesOutstanding":null,"totalAssets":9312000000.0,"totalLiabilities":3475800000.0,"totalDebt":1392200000.0,"cashAndEquivalents":253400000.0,"stockholdersEquity":5836200000.0}]}